flatten_tool/flatten/__init__.py
flatten_tool/flatten/cli.py
flatten_tool/flatten/config.py
flatten_tool/flatten/file_handler.py
flatten_tool/flatten/logging.py
flatten_tool/flatten/output.py
flatten_tool/plugins/custom_parser.py
flattenify-0.1.0.dist-info/licenses/LICENSE
flattenify-0.1.0.dist-info/METADATA
flattenify-0.1.0.dist-info/WHEEL
flattenify-0.1.0.dist-info/entry_points.txt
flattenify-0.1.0.dist-info/top_level.txt
flattenify-0.1.0.dist-info/RECORD
