Metadata-Version: 2.4
Name: flattenify
Version: 0.1.0
Summary: A CLI tool to flatten project files into a single file with descriptive paths
Author-email: Muhammed Shittu <devshittu@gmail.com>
License: MIT License
Requires-Python: >=3.8
License-File: LICENSE
Requires-Dist: tqdm==4.66.5
Requires-Dist: colorama==0.4.6
Requires-Dist: jsonschema==4.23.0
Requires-Dist: pytest==8.3.3
Provides-Extra: dev
Requires-Dist: pytest; extra == "dev"
Requires-Dist: pytest-cov; extra == "dev"
Requires-Dist: pre-commit; extra == "dev"
Requires-Dist: pytest-mock; extra == "dev"
Requires-Dist: flake8; extra == "dev"
Requires-Dist: isort; extra == "dev"
Requires-Dist: black; extra == "dev"
Dynamic: license-file
